qusi/__about__.py
qusi/__init__.py
qusi/data.py
qusi/model.py
qusi/session.py
qusi/transform.py
qusi/experimental/__init__.py
qusi/experimental/metric.py
qusi/experimental/model.py
qusi/experimental/session.py
qusi/experimental/application/__init__.py
qusi/experimental/application/tess.py
qusi/internal/__init__.py
qusi/internal/chyrin_model.py
qusi/internal/device.py
qusi/internal/finite_standard_light_curve_dataset.py
qusi/internal/finite_standard_light_curve_observation_dataset.py
qusi/internal/finite_test_session.py
qusi/internal/hadryss_model.py
qusi/internal/infer_session.py
qusi/internal/infinite_datasets_test_session.py
qusi/internal/light_curve.py
qusi/internal/light_curve_collection.py
qusi/internal/light_curve_dataset.py
qusi/internal/light_curve_observation.py
qusi/internal/light_curve_transforms.py
qusi/internal/logging.py
qusi/internal/metric.py
qusi/internal/simple_model.py
qusi/internal/single_dense_layer_model.py
qusi/internal/torran_model.py
qusi/internal/toy_light_curve_collection.py
qusi/internal/train_hyperparameter_configuration.py
qusi/internal/train_logging_configuration.py
qusi/internal/train_session.py
qusi/internal/train_system_configuration.py
qusi/internal/wandb_liaison.py
ramjet/__init__.py
ramjet/analysis/__init__.py
ramjet/analysis/color_palette.py
ramjet/analysis/convert_column_name_to_display_name.py
ramjet/analysis/light_curve_visualizer.py
ramjet/analysis/model_loader.py
ramjet/analysis/roc_calculator.py
ramjet/analysis/transit_vetter.py
ramjet/analysis/light_curve_folding_vizualizer/__init__.py
ramjet/analysis/light_curve_folding_vizualizer/application.py
ramjet/analysis/light_curve_folding_vizualizer/main.py
ramjet/analysis/light_curve_folding_vizualizer/viewer.py
ramjet/analysis/tess_ffi_variability_viewer/__init__.py
ramjet/analysis/tess_ffi_variability_viewer/main.py
ramjet/analysis/viewer/__init__.py
ramjet/analysis/viewer/light_curve_display.py
ramjet/analysis/viewer/preloader.py
ramjet/analysis/viewer/view_entity.py
qusi-1.5.6.dist-info/METADATA
qusi-1.5.6.dist-info/WHEEL
qusi-1.5.6.dist-info/RECORD
