Metadata-Version: 2.3
Name: qusi
Version: 1.5.6
Author-email: Greg Olmschenk <greg@olmschenk.com>
Requires-Python: >=3.9
Requires-Dist: astropy>=5.2.1
Requires-Dist: astroquery>=0.4.6
Requires-Dist: atpublic>=4.0
Requires-Dist: backports-strenum
Requires-Dist: beautifulsoup4>=4.11.2
Requires-Dist: bokeh>=3.0.0
Requires-Dist: filelock>=3.9.0
Requires-Dist: furo>=2023.9.10
Requires-Dist: gitpython>=3.1.30
Requires-Dist: lightkurve>=2.3.0
Requires-Dist: lxml>=4.9.2
Requires-Dist: matplotlib>=3.6.3
Requires-Dist: myst-parser
Requires-Dist: numpy<2.0.0,>=1.24.1
Requires-Dist: pandas>=1.5.3
Requires-Dist: peewee>=3.15.4
Requires-Dist: pipreqs>=0.4.11
Requires-Dist: plotly>=5.13.0
Requires-Dist: polars>=0.19.10
Requires-Dist: pyarrow>=11.0.0
Requires-Dist: pytest-asyncio>=0.20.3
Requires-Dist: pytest-pycharm>=0.7.0
Requires-Dist: pytest<8,>=7.2.1
Requires-Dist: requests>=2.28.2
Requires-Dist: retrying>=1.3.4
Requires-Dist: scipy>=1.10.0
Requires-Dist: setuptools>=67.1.0
Requires-Dist: sphinx>=6.1.3
Requires-Dist: stringcase>=1.2.0
Requires-Dist: tenacity>=8.1.0
Requires-Dist: torch>=2.0.1
Requires-Dist: torcheval>=0.0.7
Requires-Dist: torchmetrics>=1.2.0
Requires-Dist: torchvision>=0.15.2
Requires-Dist: tornado>=6.2
Requires-Dist: typing-extensions
Requires-Dist: uvloop>=0.17.0; platform_system != 'Windows'
Requires-Dist: wandb>=0.13.9
